StructuredFlow/__init__.py
StructuredFlow/main.py
StructuredFlow/prompts.py
structuredflow-2025.12.20173138.dist-info/METADATA
structuredflow-2025.12.20173138.dist-info/WHEEL
structuredflow-2025.12.20173138.dist-info/top_level.txt
structuredflow-2025.12.20173138.dist-info/RECORD
