Metadata-Version: 2.4
Name: StructuredFlow
Version: 2025.12.20173138
Summary: A new package designed to facilitate structured, reliable interactions with language models for summarizing and analyzing user input text. It receives raw or pre-processed text data as input, applies 
Author-email: StructuredFlow <hi@eugene.plus>
License: MIT
Project-URL: Homepage, https://github.com/chigwell/StructuredFlow
Requires-Python: >=3.9
Requires-Dist: langchain-llm7>=0.0.0
Requires-Dist: llmatch-messages>=0.0.0
Requires-Dist: langchain-core>=0.3.0
